setup.py
httprunner/__init__.py
httprunner/__main__.py
httprunner/cli.py
httprunner/client.py
httprunner/compat.py
httprunner/exceptions.py
httprunner/loader.py
httprunner/make.py
httprunner/models.py
httprunner/parser.py
httprunner/response.py
httprunner/runner.py
httprunner/scaffold.py
httprunner/testcase.py
httprunner/utils.py
httprunner/app/__init__.py
httprunner/app/main.py
httprunner/app/routers/__init__.py
httprunner/app/routers/debug.py
httprunner/app/routers/debugtalk.py
httprunner/app/routers/deps.py
httprunner/builtin/__init__.py
httprunner/builtin/comparators.py
httprunner/builtin/functions.py
httprunner/ext/__init__.py
httprunner/ext/har2case/__init__.py
httprunner/ext/har2case/core.py
httprunner/ext/har2case/utils.py
httprunner/ext/locust/__init__.py
httprunner/ext/locust/locustfile.py
httprunner/ext/uploader/__init__.py
mk_httprunner.egg-info/PKG-INFO
mk_httprunner.egg-info/SOURCES.txt
mk_httprunner.egg-info/dependency_links.txt
mk_httprunner.egg-info/not-zip-safe
mk_httprunner.egg-info/top_level.txt