Metadata-Version: 1.0
Name: mk-httprunner
Version: 3.1.4.2
Summary: httprunner by mk
Home-page: https://gitlab.mockuai.com/qa/mk_run.git
Author: yexiebiao
Author-email: 228289823@qq.com
License: MIT
Platform: UNKNOWN
